excitingtools/__init__.py
excitingtools/py.typed
excitingtools/base/__init__.py
excitingtools/base/serialisation.py
excitingtools/constants/units.py
excitingtools/dataclasses/__init__.py
excitingtools/dataclasses/band_structure.py
excitingtools/dataclasses/data_structs.py
excitingtools/dataclasses/density_of_states.py
excitingtools/dataclasses/eigenvalues.py
excitingtools/eigenstates/eigenstates.py
excitingtools/exciting_dict_parsers/RT_TDDFT_parser.py
excitingtools/exciting_dict_parsers/__init__.py
excitingtools/exciting_dict_parsers/bse_parser.py
excitingtools/exciting_dict_parsers/groundstate_parser.py
excitingtools/exciting_dict_parsers/gw_eigenvalues_parser.py
excitingtools/exciting_dict_parsers/gw_eps00_parser.py
excitingtools/exciting_dict_parsers/gw_info_parser.py
excitingtools/exciting_dict_parsers/gw_taskgroup_parser.py
excitingtools/exciting_dict_parsers/gw_vxc_parser.py
excitingtools/exciting_dict_parsers/hdf5_parser.py
excitingtools/exciting_dict_parsers/input_parser.py
excitingtools/exciting_dict_parsers/parser_factory.py
excitingtools/exciting_dict_parsers/phonon_parser.py
excitingtools/exciting_dict_parsers/properties_parser.py
excitingtools/exciting_dict_parsers/species_parser.py
excitingtools/exciting_dict_parsers/state_parser.py
excitingtools/exciting_obj_parsers/__init__.py
excitingtools/exciting_obj_parsers/eigenvalue_parser.py
excitingtools/exciting_obj_parsers/gw_eigenvalues.py
excitingtools/exciting_obj_parsers/input_xml.py
excitingtools/exciting_obj_parsers/ks_band_structure.py
excitingtools/input/__init__.py
excitingtools/input/bandstructure.py
excitingtools/input/base_class.py
excitingtools/input/dynamic_class.py
excitingtools/input/input_classes.py
excitingtools/input/input_xml.py
excitingtools/input/structure.py
excitingtools/input/xml_utils.py
excitingtools/math/__init__.py
excitingtools/math/math_utils.py
excitingtools/parser_utils/__init__.py
excitingtools/parser_utils/erroneous_file_error.py
excitingtools/parser_utils/grep_parser.py
excitingtools-1.8.3.dist-info/licenses/COPYING.LESSER
excitingtools-1.8.3.dist-info/licenses/COPYING.md
excitingtools-1.8.3.dist-info/METADATA
excitingtools-1.8.3.dist-info/WHEEL
excitingtools-1.8.3.dist-info/top_level.txt
excitingtools-1.8.3.dist-info/RECORD
