Metadata-Version: 2.4
Name: excitingtools
Version: 1.8.3
Summary: Utilities for aiding in the construction of exciting inputs and the postprocessing exciting outputs.
Author-email: Alexander Buccheri <alexander.buccheri@mpsd.mpg.de>, Fabian Peschel <peschelf@physik.hu-berlin.de>
License: GNU GENERAL PUBLIC LICENSE, see 'COPYING.md'
Project-URL: repository, https://github.com/exciting/excitingtools
Requires-Python: >=3.7
License-File: COPYING.LESSER
License-File: COPYING.md
Requires-Dist: numpy>=1.20.0
Requires-Dist: matplotlib>=2.2.0
Requires-Dist: importlib-metadata>=6.0; python_version < "3.8"
Provides-Extra: dev
Requires-Dist: pytest; extra == "dev"
Requires-Dist: ase>=3.20.0; extra == "dev"
Requires-Dist: ruff==0.11.2; extra == "dev"
Provides-Extra: schemaparsing
Requires-Dist: xmlschema; extra == "schemaparsing"
Provides-Extra: h5-parsing
Requires-Dist: h5py; extra == "h5-parsing"
Provides-Extra: serialisation
Requires-Dist: monty; extra == "serialisation"
Dynamic: license-file
